fpng_py/__init__.py
fpng_py/_fpng_py.cp38-win_amd64.pyd
fpng_py-0.0.3.dist-info/LICENSE
fpng_py-0.0.3.dist-info/METADATA
fpng_py-0.0.3.dist-info/WHEEL
fpng_py-0.0.3.dist-info/top_level.txt
fpng_py-0.0.3.dist-info/RECORD
