Metadata-Version: 2.1
Name: fpng-py
Version: 0.0.3
Home-page: https://github.com/K0lb3/fpng_py
Download-URL: https://github.com/K0lb3/fpng_py/tarball/master
Author: K0lb3
Keywords: png,compression
Classifier: License :: OSI Approved :: MIT License
Classifier: Operating System :: OS Independent
Classifier: Intended Audience :: Developers
Classifier: Programming Language :: Python
Classifier: Programming Language :: Python :: 3
Classifier: Topic :: Multimedia :: Graphics
License-File: LICENSE
